ament_cmake_export_interfaces/_dummy.cpython-310-x86_64-linux-gnu.so
ros_ament_cmake_export_interfaces-2.7.3.data/data/share/ament_cmake_export_interfaces/local_setup.bash
ros_ament_cmake_export_interfaces-2.7.3.data/data/share/ament_cmake_export_interfaces/local_setup.dsv
ros_ament_cmake_export_interfaces-2.7.3.data/data/share/ament_cmake_export_interfaces/local_setup.sh
ros_ament_cmake_export_interfaces-2.7.3.data/data/share/ament_cmake_export_interfaces/local_setup.zsh
ros_ament_cmake_export_interfaces-2.7.3.data/data/share/ament_cmake_export_interfaces/package.dsv
ros_ament_cmake_export_interfaces-2.7.3.data/data/share/ament_cmake_export_interfaces/package.xml
ros_ament_cmake_export_interfaces-2.7.3.data/data/share/ament_cmake_export_interfaces/cmake/ament_cmake_export_interfaces-extras.cmake
ros_ament_cmake_export_interfaces-2.7.3.data/data/share/ament_cmake_export_interfaces/cmake/ament_cmake_export_interfaces-extras.cmake.in
ros_ament_cmake_export_interfaces-2.7.3.data/data/share/ament_cmake_export_interfaces/cmake/ament_cmake_export_interfacesConfig-version.cmake
ros_ament_cmake_export_interfaces-2.7.3.data/data/share/ament_cmake_export_interfaces/cmake/ament_cmake_export_interfacesConfig.cmake
ros_ament_cmake_export_interfaces-2.7.3.data/data/share/ament_cmake_export_interfaces/cmake/ament_cmake_export_interfaces_package_hook.cmake
ros_ament_cmake_export_interfaces-2.7.3.data/data/share/ament_cmake_export_interfaces/cmake/ament_export_interfaces.cmake
ros_ament_cmake_export_interfaces-2.7.3.data/data/share/ament_cmake_export_interfaces/environment/ament_prefix_path.dsv
ros_ament_cmake_export_interfaces-2.7.3.data/data/share/ament_cmake_export_interfaces/environment/ament_prefix_path.sh
ros_ament_cmake_export_interfaces-2.7.3.data/data/share/ament_cmake_export_interfaces/environment/path.dsv
ros_ament_cmake_export_interfaces-2.7.3.data/data/share/ament_cmake_export_interfaces/environment/path.sh
ros_ament_cmake_export_interfaces-2.7.3.dist-info/METADATA
ros_ament_cmake_export_interfaces-2.7.3.dist-info/WHEEL
ros_ament_cmake_export_interfaces-2.7.3.dist-info/top_level.txt
ros_ament_cmake_export_interfaces-2.7.3.dist-info/RECORD
